README.md
setup.py
pytest_hue/__init__.py
pytest_hue/_plugin.py
pytest_hue/_reporter.py
pytest_hue.egg-info/PKG-INFO
pytest_hue.egg-info/SOURCES.txt
pytest_hue.egg-info/dependency_links.txt
pytest_hue.egg-info/entry_points.txt
pytest_hue.egg-info/requires.txt
pytest_hue.egg-info/top_level.txt