Metadata-Version: 2.1
Name: pytest-hue
Version: 1.0.0
Summary: Visualise PyTest status via your Phillips Hue lights
Home-page: https://github.com/Gimpneek/pytest-hue
Author: Colin Wren
Author-email: gimpneek@gmail.com
License: GPLv3
Keywords: py.test pytest phillips hue lights report
Platform: UNKNOWN
Classifier: Framework :: Pytest
Classifier: Operating System :: Microsoft :: Windows
Classifier: Operating System :: MacOS :: MacOS X
Classifier: Operating System :: POSIX
Classifier: Operating System :: Unix
Classifier: Programming Language :: Python
Classifier: Programming Language :: Python :: 2
Classifier: Programming Language :: Python :: 2.7
Classifier: Programming Language :: Python :: 3
Classifier: Programming Language :: Python :: 3.4
Classifier: Programming Language :: Python :: 3.5
Classifier: Programming Language :: Python :: 3.6
Classifier: Programming Language :: Python :: 3.7
Classifier: Programming Language :: Python :: Implementation :: CPython
Classifier: Programming Language :: Python :: Implementation :: PyPy
Classifier: License :: OSI Approved :: GNU General Public License (GPL)
Provides-Extra: test
